trainy/__init__.py
trainy/config.py
trainy/configs/eks.yaml
trainy/configs/gke.yaml
trainy/configs/nebius.yaml
trainy/logging.py
trainy/policy/__init__.py
trainy/policy/eks.py
trainy/policy/gke.py
trainy/policy/nebius.py
trainy_policy_nightly-0.1.0.dev20260201105445.dist-info/METADATA
trainy_policy_nightly-0.1.0.dev20260201105445.dist-info/WHEEL
trainy_policy_nightly-0.1.0.dev20260201105445.dist-info/RECORD
