Metadata-Version: 2.1
Name: trainy-policy-nightly
Version: 0.1.0.dev20260201105445
Summary: Trainy Skypilot Policy
Author: Andrew Aikawa
Author-email: asai@berkeley.edu
Requires-Python: >=3.9,<4.0
Classifier: Programming Language :: Python :: 3
Classifier: Programming Language :: Python :: 3.9
Classifier: Programming Language :: Python :: 3.10
Classifier: Programming Language :: Python :: 3.11
Classifier: Programming Language :: Python :: 3.12
Requires-Dist: kubernetes (>=30.1.0,<31.0.0)
